buttshock/__init__.py
buttshock/errors.py
buttshock/2b/__init__.py
buttshock/et232/__init__.py
buttshock/et312/__init__.py
buttshock/et312/base.py
buttshock/et312/comm.py
buttshock/et312/emulator.py
buttshock-0.2.1.dist-info/DESCRIPTION.rst
buttshock-0.2.1.dist-info/METADATA
buttshock-0.2.1.dist-info/RECORD
buttshock-0.2.1.dist-info/WHEEL
buttshock-0.2.1.dist-info/metadata.json
buttshock-0.2.1.dist-info/top_level.txt
